CHANGELOG.md
development.json
development.yaml
pyramid_helloworld-2.0.5.dist-info/METADATA
pyramid_helloworld-2.0.5.dist-info/WHEEL
pyramid_helloworld-2.0.5.dist-info/entry_points.txt
pyramid_helloworld-2.0.5.dist-info/licenses/LICENSE
pyramid_helloworld/__init__.py
pyramid_helloworld/backend.py
pyramid_helloworld/tasks.py
pyramid_helloworld-2.0.5.dist-info/RECORD
